__init__.py
transform_data_schema/__init__.py
transform_data_schema/auto_replace_validate_error_field.py
transform_data_schema/base_schema.py
transform_data_schema/transform_fields.py
transform_data_schema/transform_handler.py
transform_data_schema/utils.py
transform_data_schema-1.2.5.dist-info/METADATA
transform_data_schema-1.2.5.dist-info/WHEEL
transform_data_schema-1.2.5.dist-info/top_level.txt
transform_data_schema-1.2.5.dist-info/RECORD
