Metadata-Version: 2.1
Name: transform-data-schema
Version: 1.2.5
Summary: Define the shape and validate data
Author-email: Hieucaohd <hieucaohd@gmail.com>
Project-URL: Homepage, https://github.com/Hieucaohd/transform-data-schema
Keywords: schema,validate
Classifier: License :: OSI Approved :: MIT License
Classifier: Programming Language :: Python
Classifier: Programming Language :: Python :: 3
Requires-Python: >=3.8
Requires-Dist: marshmallow
Requires-Dist: tomli ; python_version < "3.11"
Provides-Extra: dev
Requires-Dist: black ; extra == 'dev'
Requires-Dist: bumpver ; extra == 'dev'
Requires-Dist: isort ; extra == 'dev'
Requires-Dist: pip-tools ; extra == 'dev'
Requires-Dist: pytest ; extra == 'dev'
